hipsaint/__init__.py
hipsaint/messages.py
hipsaint/options.py
hipsaint/templates.py
hipsaint/tests.py
hipsaint/bin/__init__.py
hipsaint/bin/commands.py
hipsaint-0.7.dist-info/DESCRIPTION.rst
hipsaint-0.7.dist-info/METADATA
hipsaint-0.7.dist-info/RECORD
hipsaint-0.7.dist-info/WHEEL
hipsaint-0.7.dist-info/entry_points.txt
hipsaint-0.7.dist-info/metadata.json
hipsaint-0.7.dist-info/top_level.txt
