Metadata-Version: 2.0
Name: hipsaint
Version: 0.7
Summary: A command line tool for pushing Nagios host and service notifications to a HipChat room.
Home-page: http://github.com/hannseman/hipsaint
Author: Hannes Ljungberg
Author-email: hannes@5monkeys.se
License: WTFPL
Download-URL: https://github.com/hannseman/hipsaint/tarball/0.7
Keywords: nagios,hipchat,api,plugin
Platform: UNKNOWN
Classifier: Programming Language :: Python
Classifier: Programming Language :: Python :: 2
Classifier: Programming Language :: Python :: 2.6
Classifier: Programming Language :: Python :: 2.7
Classifier: Programming Language :: Python :: 3
Classifier: Development Status :: 3 - Alpha
Classifier: Natural Language :: English
Classifier: Environment :: Console
Classifier: Intended Audience :: Developers
Classifier: Intended Audience :: System Administrators
Classifier: Operating System :: OS Independent
Classifier: Topic :: Utilities
